MCP_Server/__init__.py
MCP_Server/server.py
vibe_music_prod_server-1.0.0.dist-info/licenses/LICENSE
vibe_music_prod_server-1.0.0.dist-info/METADATA
vibe_music_prod_server-1.0.0.dist-info/WHEEL
vibe_music_prod_server-1.0.0.dist-info/entry_points.txt
vibe_music_prod_server-1.0.0.dist-info/top_level.txt
vibe_music_prod_server-1.0.0.dist-info/RECORD
