Metadata-Version: 2.4
Name: vibe-music-prod-server
Version: 1.0.0
Summary: Ableton Live integration through the Model Context Protocol (forked and customized)
Author: Example Author
Author-email: Moshik Mishaeli <motzik88@gmail.com>
License: MIT
Project-URL: Homepage, https://github.com/ResearchLLM/vibe-music-prod-server
Project-URL: Bug Tracker, https://github.com/ResearchLLM/vibe-music-prod-server/issues
Classifier: Programming Language :: Python :: 3
Classifier: License :: OSI Approved :: MIT License
Classifier: Operating System :: OS Independent
Requires-Python: >=3.10
License-File: LICENSE
Requires-Dist: mcp[cli]>=1.3.0
Dynamic: author
Dynamic: license-file
Dynamic: requires-python
